{
  "fechaHoraActualizacion": "2026-07-02T11:28:26.3999714",
  "categorias": {
    "Ingeniería": {
      "ofertasEntradas": 7,
      "ofertasSalidas": 1,
      "pedidosEntradas": 0,
      "pedidosSalidas": 6
    },
    "Automáticos": {
      "ofertasEntradas": 4,
      "ofertasSalidas": 2,
      "pedidosEntradas": 0,
      "pedidosSalidas": 0
    },
    "ISAs": {
      "ofertasEntradas": 0,
      "ofertasSalidas": 0,
      "pedidosEntradas": 0,
      "pedidosSalidas": 0
    },
    "VE": {
      "ofertasEntradas": 0,
      "ofertasSalidas": 0,
      "pedidosEntradas": 0,
      "pedidosSalidas": 4
    }
  }
}