{
  "fechaHoraActualizacion": "2026-05-18T09:47:48.9663727",
  "categorias": {
    "Ingeniería": {
      "ofertasEntradas": 2,
      "ofertasSalidas": 2,
      "pedidosEntradas": 5,
      "pedidosSalidas": 4
    },
    "Automáticos": {
      "ofertasEntradas": 3,
      "ofertasSalidas": 0,
      "pedidosEntradas": 1,
      "pedidosSalidas": 0
    },
    "ISAs": {
      "ofertasEntradas": 0,
      "ofertasSalidas": 0,
      "pedidosEntradas": 0,
      "pedidosSalidas": 1
    },
    "VE": {
      "ofertasEntradas": 0,
      "ofertasSalidas": 0,
      "pedidosEntradas": 1,
      "pedidosSalidas": 3
    }
  }
}