{
  "fechaHoraActualizacion": "2026-07-21T13:08:09.660816",
  "categorias": {
    "Ingeniería": {
      "ofertasEntradas": 7,
      "ofertasSalidas": 12,
      "pedidosEntradas": 0,
      "pedidosSalidas": 5
    },
    "Automáticos": {
      "ofertasEntradas": 5,
      "ofertasSalidas": 0,
      "pedidosEntradas": 1,
      "pedidosSalidas": 0
    },
    "ISAs": {
      "ofertasEntradas": 0,
      "ofertasSalidas": 0,
      "pedidosEntradas": 1,
      "pedidosSalidas": 1
    },
    "VE": {
      "ofertasEntradas": 0,
      "ofertasSalidas": 0,
      "pedidosEntradas": 0,
      "pedidosSalidas": 2
    }
  }
}