{
  "fechaHoraActualizacion": "2026-06-04T17:48:04.6683145",
  "categorias": {
    "Ingeniería": {
      "ofertasEntradas": 6,
      "ofertasSalidas": 8,
      "pedidosEntradas": 1,
      "pedidosSalidas": 7
    },
    "Automáticos": {
      "ofertasEntradas": 1,
      "ofertasSalidas": 3,
      "pedidosEntradas": 1,
      "pedidosSalidas": 1
    },
    "ISAs": {
      "ofertasEntradas": 0,
      "ofertasSalidas": 0,
      "pedidosEntradas": 0,
      "pedidosSalidas": 1
    },
    "VE": {
      "ofertasEntradas": 0,
      "ofertasSalidas": 0,
      "pedidosEntradas": 1,
      "pedidosSalidas": 7
    }
  }
}