{
  "fechaHoraActualizacion": "2026-03-05T12:23:53.0153851",
  "categorias": {
    "Ingeniería": {
      "ofertasEntradas": 12,
      "ofertasSalidas": 9,
      "pedidosEntradas": 3,
      "pedidosSalidas": 0
    },
    "Automáticos": {
      "ofertasEntradas": 2,
      "ofertasSalidas": 0,
      "pedidosEntradas": 0,
      "pedidosSalidas": 1
    },
    "ISAs": {
      "ofertasEntradas": 0,
      "ofertasSalidas": 0,
      "pedidosEntradas": 0,
      "pedidosSalidas": 0
    },
    "VE": {
      "ofertasEntradas": 0,
      "ofertasSalidas": 0,
      "pedidosEntradas": 1,
      "pedidosSalidas": 6
    }
  }
}