{
  "fechaHoraActualizacion": "2026-06-11T12:03:16.3892992",
  "categorias": {
    "Ingeniería": {
      "ofertasEntradas": 6,
      "ofertasSalidas": 6,
      "pedidosEntradas": 0,
      "pedidosSalidas": 2
    },
    "Automáticos": {
      "ofertasEntradas": 5,
      "ofertasSalidas": 0,
      "pedidosEntradas": 2,
      "pedidosSalidas": 1
    },
    "ISAs": {
      "ofertasEntradas": 0,
      "ofertasSalidas": 0,
      "pedidosEntradas": 0,
      "pedidosSalidas": 0
    },
    "VE": {
      "ofertasEntradas": 0,
      "ofertasSalidas": 0,
      "pedidosEntradas": 0,
      "pedidosSalidas": 4
    }
  }
}