{
  "fechaHoraActualizacion": "2026-02-27T12:55:39.7777422",
  "categorias": {
    "Ingeniería": {
      "ofertasEntradas": 10,
      "ofertasSalidas": 16,
      "pedidosEntradas": 2,
      "pedidosSalidas": 6
    },
    "Automáticos": {
      "ofertasEntradas": 4,
      "ofertasSalidas": 2,
      "pedidosEntradas": 1,
      "pedidosSalidas": 1
    },
    "ISAs": {
      "ofertasEntradas": 0,
      "ofertasSalidas": 0,
      "pedidosEntradas": 0,
      "pedidosSalidas": 0
    },
    "VE": {
      "ofertasEntradas": 0,
      "ofertasSalidas": 0,
      "pedidosEntradas": 1,
      "pedidosSalidas": 1
    }
  }
}