{
  "fechaHoraActualizacion": "2026-03-30T16:11:35.699252",
  "categorias": {
    "Ingeniería": {
      "ofertasEntradas": 9,
      "ofertasSalidas": 4,
      "pedidosEntradas": 1,
      "pedidosSalidas": 2
    },
    "Automáticos": {
      "ofertasEntradas": 3,
      "ofertasSalidas": 0,
      "pedidosEntradas": 1,
      "pedidosSalidas": 1
    },
    "ISAs": {
      "ofertasEntradas": 0,
      "ofertasSalidas": 0,
      "pedidosEntradas": 0,
      "pedidosSalidas": 0
    },
    "VE": {
      "ofertasEntradas": 0,
      "ofertasSalidas": 0,
      "pedidosEntradas": 0,
      "pedidosSalidas": 1
    }
  }
}