{
  "fechaHoraActualizacion": "2026-03-10T18:03:14.9196067",
  "categorias": {
    "Ingeniería": {
      "ofertasEntradas": 10,
      "ofertasSalidas": 8,
      "pedidosEntradas": 3,
      "pedidosSalidas": 10
    },
    "Automáticos": {
      "ofertasEntradas": 2,
      "ofertasSalidas": 4,
      "pedidosEntradas": 0,
      "pedidosSalidas": 1
    },
    "ISAs": {
      "ofertasEntradas": 0,
      "ofertasSalidas": 0,
      "pedidosEntradas": 0,
      "pedidosSalidas": 0
    },
    "VE": {
      "ofertasEntradas": 0,
      "ofertasSalidas": 0,
      "pedidosEntradas": 0,
      "pedidosSalidas": 6
    }
  }
}